mrodent_lib/__init__.py
mrodent_lib/configure_logging.py
mrodent_lib/constants_lib.py
mrodent_lib/experiment_for_configuring_logging.py
mrodent_lib/pyt.py
mrodent_lib/single_instance_checker.py
mrodent_lib/try_logging.py
mrodent_lib-1.3.1.dist-info/WHEEL
mrodent_lib-1.3.1.dist-info/entry_points.txt
mrodent_lib-1.3.1.dist-info/METADATA
mrodent_lib-1.3.1.dist-info/RECORD
