Metadata-Version: 2.3
Name: mrodent-lib
Version: 1.3.1
Summary: Library package with various utilities
Author: chris
Author-email: chris <post@chris-scully.co.uk>
Requires-Dist: colorlog>=6.10.1
Requires-Dist: concurrent-log-handler>=0.9.28
Requires-Python: >=3.13
